{"_type":"export","__export_format":4,"__export_date":"2021-06-17T01:50:50.920Z","__export_source":"insomnia.desktop.app:v2021.3.0","resources":[{"_id":"req_8f8ecffab7af4032984d18d8c83a59f0","parentId":"fld_293441266e174761874d2ccd134518fb","modified":1623883105420,"created":1623883030096,"url":"{{ _.base_url }}/{{ _.resource }}/","name":"List Author Articles","description":"","method":"GET","body":{},"parameters":[],"headers":[],"authentication":{"type":"bearer","token":"{% response 'body', 'req_943f476990a841268c87cd6b14c1fbda', 'b64::JC50b2tlbg==::46b', 'when-expired', 14400 %}"},"metaSortKey":-1623883030096,"isPrivate":false,"settingStoreCookies":true,"settingSendCookies":true,"settingDisableRenderRequestBody":false,"settingEncodeUrl":true,"settingRebuildPath":true,"settingFollowRedirects":"global","_type":"request"},{"_id":"fld_293441266e174761874d2ccd134518fb","parentId":"wrk_eeb449a2cabb4e8cbd3888a7db0231d5","modified":1623792655053,"created":1623792621243,"name":"Articles","description":"","environment":{"resource":"articles"},"environmentPropertyOrder":{"&":["resource"]},"metaSortKey":-1623792621243,"_type":"request_group"},{"_id":"wrk_eeb449a2cabb4e8cbd3888a7db0231d5","parentId":null,"modified":1623005844339,"created":1623005844340,"name":"Tog Design","description":"","scope":"collection","_type":"workspace"},{"_id":"req_1d20af92af22498aabe688cf05a0bbba","parentId":"fld_293441266e174761874d2ccd134518fb","modified":1623880221027,"created":1623798176473,"url":"{{ _.base_url }}/{{ _.resource }}/{% response 'body', 'req_5fbbc8e7f70b422dbc7003f1eb1f3cc8', 'b64::JC5pZA==::46b', 'no-history', 60 %}","name":"Show","description":"","method":"GET","body":{},"parameters":[],"headers":[],"authentication":{"type":"bearer","token":"{% response 'body', 'req_943f476990a841268c87cd6b14c1fbda', 'b64::JC50b2tlbg==::46b', 'when-expired', 14400 %}","disabled":false},"metaSortKey":-1623798176473,"isPrivate":false,"settingStoreCookies":true,"settingSendCookies":true,"settingDisableRenderRequestBody":false,"settingEncodeUrl":true,"settingRebuildPath":true,"settingFollowRedirects":"global","_type":"request"},{"_id":"req_5fbbc8e7f70b422dbc7003f1eb1f3cc8","parentId":"fld_293441266e174761874d2ccd134518fb","modified":1623880041314,"created":1623792631566,"url":"{{ _.base_url }}/{{ _.resource }}","name":"Create","description":"","method":"POST","body":{"mimeType":"multipart/form-data","params":[{"name":"cover","value":"","description":"","id":"pair_f5b49ca666274d6c8ec60b7cabded58a","type":"file","fileName":"C:\\Users\\Felipe\\Downloads\\teste.jpg"},{"name":"title","value":"Lorem ipsum dolor sit amet","description":"","id":"pair_6f96e8495d594c099ed2f6eb9463d721"},{"name":"text","value":"Lorem ipsum dolor sit amet, consectetur adipiscing elit. Sed ante magna, pulvinar nec aliquet ut, blandit id diam. Duis dignissim, erat a varius dignissim, nulla ipsum commodo tortor, vel fermentum nunc orci et sem. Fusce hendrerit, ex id convallis ultrices, dolor mauris ullamcorper libero, non pellentesque libero nisi sed diam. Aliquam erat volutpat. Etiam ornare volutpat scelerisque. Donec blandit cursus purus, sit amet maximus arcu faucibus nec. Pellentesque consectetur porta purus, quis blandit nisl placerat luctus. Curabitur pharetra efficitur massa sit amet efficitur. Suspendisse vestibulum eros nisi, sed fermentum arcu faucibus in. Duis posuere odio eu sagittis sollicitudin. Ut in feugiat enim. Sed sollicitudin gravida sagittis. Nunc ultricies porttitor odio ac consectetur. Suspendisse id enim eu libero commodo eleifend ornare non nibh. Aliquam convallis neque non quam feugiat, at commodo odio pretium. Donec sed ullamcorper nulla. Aenean lobortis malesuada ipsum, et sagittis sem luctus ut. Cras in vestibulum velit, vel euismod lacus. Nunc mollis magna in libero tristique, vitae efficitur massa blandit. Nullam et arcu interdum, hendrerit lectus non, rhoncus quam. Proin eu rutrum risus. Cras metus sem, iaculis vitae commodo sed, posuere at ex. Nunc nulla mauris, sodales ac leo eu, semper rutrum justo. Vestibulum quis dui auctor, feugiat nunc sit amet, pellentesque ipsum. Sed non blandit orci. Quisque elementum vel lacus vitae vulputate. Nunc cursus massa eu ex tristique, in aliquet ex pellentesque.","description":"","id":"pair_4417f8b5a709459ab98e17736b2f4f7c","type":"text","multiline":true},{"name":"themes","value":"Lorem","description":"","id":"pair_b8d81d0c5b6147ac95c091504db09289"},{"name":"themes","value":"Ipsum","description":"","id":"pair_59a64e1d216243248fd241fc1ec53127"},{"name":"themes","value":"Dolor","description":"","id":"pair_ca5b5464a39246f79790ab191c288207"},{"name":"themes","value":"Sit","description":"","id":"pair_918ddebac6c94bb09920ac2e609d0166"},{"name":"themes","value":"Amet","description":"","id":"pair_17ecc2c1bc794498b32a52d9eeffb371","disabled":false},{"name":"category_id","value":"{% response 'body', 'req_93c8a313cd424cfda7e056a8a92d1710', 'b64::JFswXS5pZA==::46b', 'no-history', 60 %}","description":"","id":"pair_b2f6461a537e465490f560c973c03f28"}]},"parameters":[],"headers":[{"name":"Content-Type","value":"multipart/form-data","id":"pair_dfa8649102824dfbb6c9a2a092ae1267"}],"authentication":{"type":"bearer","token":"{% response 'body', 'req_943f476990a841268c87cd6b14c1fbda', 'b64::JC50b2tlbg==::46b', 'when-expired', 14400 %}"},"metaSortKey":-1623792631566,"isPrivate":false,"settingStoreCookies":true,"settingSendCookies":true,"settingDisableRenderRequestBody":false,"settingEncodeUrl":true,"settingRebuildPath":true,"settingFollowRedirects":"global","_type":"request"},{"_id":"req_93c8a313cd424cfda7e056a8a92d1710","parentId":"fld_c23539bcb62345b495888d98b3a30315","modified":1623792606644,"created":1623792593974,"url":"{{ _.base_url }}/{{ _.resource }}","name":"Index","description":"","method":"GET","body":{},"parameters":[],"headers":[],"authentication":{},"metaSortKey":-1623792593974,"isPrivate":false,"settingStoreCookies":true,"settingSendCookies":true,"settingDisableRenderRequestBody":false,"settingEncodeUrl":true,"settingRebuildPath":true,"settingFollowRedirects":"global","_type":"request"},{"_id":"fld_c23539bcb62345b495888d98b3a30315","parentId":"wrk_eeb449a2cabb4e8cbd3888a7db0231d5","modified":1623792584894,"created":1623792572940,"name":"Categories","description":"","environment":{"resource":"categories"},"environmentPropertyOrder":{"&":["resource"]},"metaSortKey":-1623792572940,"_type":"request_group"},{"_id":"req_943f476990a841268c87cd6b14c1fbda","parentId":"fld_bc131e1368974be4b5960ac49cb6cdf1","modified":1623010278484,"created":1623010168351,"url":"{{ _.base_url }}/{{ _.resource }}","name":"Authenticate","description":"","method":"POST","body":{"mimeType":"application/json","text":"{\n\t\"email\": \"johndoe@example.com\",\n\t\"password\": \"12345678\"\n}"},"parameters":[],"headers":[{"name":"Content-Type","value":"application/json","id":"pair_ad4e896375684d00ae661825473e38cd"}],"authentication":{},"metaSortKey":-1623010168351,"isPrivate":false,"settingStoreCookies":true,"settingSendCookies":true,"settingDisableRenderRequestBody":false,"settingEncodeUrl":true,"settingRebuildPath":true,"settingFollowRedirects":"global","_type":"request"},{"_id":"fld_bc131e1368974be4b5960ac49cb6cdf1","parentId":"wrk_eeb449a2cabb4e8cbd3888a7db0231d5","modified":1623010199227,"created":1623010158211,"name":"Sessions","description":"","environment":{"resource":"sessions"},"environmentPropertyOrder":{"&":["resource"]},"metaSortKey":-1623010158211,"_type":"request_group"},{"_id":"req_c7c8290c01b94356a3babaf024f22366","parentId":"fld_8c4c68ca3c514b059448560d348b0dfd","modified":1623792639465,"created":1623006427371,"url":"{{ _.base_url }}/{{ _.resource }}","name":"Create","description":"","method":"POST","body":{"mimeType":"application/json","text":"{\n\t\"name\": \"John Doe\",\n\t\"email\": \"johndoe@example.com\",\n\t\"password\": \"12345678\"\n}"},"parameters":[],"headers":[{"name":"Content-Type","value":"application/json","id":"pair_10eb752815434c3eb150c499471efaeb"}],"authentication":{},"metaSortKey":-1623006427371,"isPrivate":false,"settingStoreCookies":true,"settingSendCookies":true,"settingDisableRenderRequestBody":false,"settingEncodeUrl":true,"settingRebuildPath":true,"settingFollowRedirects":"global","_type":"request"},{"_id":"fld_8c4c68ca3c514b059448560d348b0dfd","parentId":"wrk_eeb449a2cabb4e8cbd3888a7db0231d5","modified":1623010183109,"created":1623006430427,"name":"Users","description":"","environment":{"resource":"users"},"environmentPropertyOrder":{"&":["resource"]},"metaSortKey":-1623006430427,"_type":"request_group"},{"_id":"env_6da7e35d159c4ee89baaf6d242cb9407b70b2872","parentId":"wrk_eeb449a2cabb4e8cbd3888a7db0231d5","modified":1623005844432,"created":1623005844432,"name":"Base Environment","data":{},"dataPropertyOrder":null,"color":null,"isPrivate":false,"metaSortKey":1623005844432,"_type":"environment"},{"_id":"jar_6da7e35d159c4ee89baaf6d242cb9407b70b2872","parentId":"wrk_eeb449a2cabb4e8cbd3888a7db0231d5","modified":1623005844440,"created":1623005844440,"name":"Default Jar","cookies":[],"_type":"cookie_jar"},{"_id":"spc_27689901e58541488f7b54c536ba55d9","parentId":"wrk_eeb449a2cabb4e8cbd3888a7db0231d5","modified":1623005844346,"created":1623005844346,"fileName":"Tog Design","contents":"","contentType":"yaml","_type":"api_spec"},{"_id":"env_6410da9a92d24264b94abb7e9c600733","parentId":"env_6da7e35d159c4ee89baaf6d242cb9407b70b2872","modified":1623006410010,"created":1623006374711,"name":"Dev","data":{"base_url":"http://localhost:3333"},"dataPropertyOrder":{"&":["base_url"]},"color":"#05e6e2","isPrivate":false,"metaSortKey":1623006374711,"_type":"environment"}]}